{"layout": "`[3q10;6z'2/]5flu-4wrcx7=\\boeivyntak,jmhp8.dsg9", "total_distance": 8942963.65444032, "valid_chars": 4769179, "invalid_chars": 992642, "efficiency": 1.875157894983669, "dataset_names": ["brown/brown_A.txt", "brown/brown_B.txt", "brown/brown_C.txt", "brown/brown_D.txt", "brown/brown_E.txt", "brown/brown_F.txt", "brown/brown_G.txt", "brown/brown_H.txt", "brown/brown_J.txt", "brown/brown_K.txt", "brown/brown_L.txt", "brown/brown_M.txt", "brown/brown_N.txt", "brown/brown_P.txt", "brown/brown_R.txt"], "last_analysis": "2022-11-22-23:39:05", "name": "keyboards/2022-11-22-23:39:05"}